{
    "version": "5.2.2",
    "description": "Simple and Convenient Messaging App for VK",
    "homepage": "https://vk.com/desktop_app",
    "license": "Unknown",
    "architecture": {
        "64bit": {
            "url": "https://desktop.userapi.com/win64/master/latest.zip",
            "hash": "2b4d17c18b88896720a518f2660fb2880bea51d47b509f1a773a44631488073d"
        },
        "32bit": {
            "url": "https://desktop.userapi.com/win32/master/latest.zip",
            "hash": "6e83100ba3023f2329814032f54f8accd52ee808fe5e9e8cc144cde32aeddb41"
        }
    },
    "bin": "vk.exe",
    "shortcuts": [
        [
            "vk.exe",
            "VK Messenger"
        ]
    ],
    "checkver": {
        "url": "https://desktop.userapi.com/check_update?platform=win64&branch=master&lang=en",
        "jp": "$.version"
    },
    "autoupdate": {
        "architecture": {
            "64bit": {
                "url": "https://desktop.userapi.com/win64/master/latest.zip"
            },
            "32bit": {
                "url": "https://desktop.userapi.com/win32/master/latest.zip"
            }
        }
    }
}
